pyworkbox/__init__.py
pyworkbox/core.py
pyworkbox-0.0.4.dist-info/licenses/LICENSE
pyworkbox-0.0.4.dist-info/METADATA
pyworkbox-0.0.4.dist-info/WHEEL
pyworkbox-0.0.4.dist-info/top_level.txt
pyworkbox-0.0.4.dist-info/RECORD
