Metadata-Version: 2.4
Name: pyworkbox
Version: 0.0.4
Summary: A collection of my awesome Python functions to make life easier.
Author-email: mengvision <mengvision@qq.com>
License: MIT License
Project-URL: Homepage, https://github.com/mengvision/pyworkbox
Project-URL: Documentation, https://github.com/mengvision/pyworkbox#readme
Project-URL: Issues, https://github.com/mengvision/pyworkbox/issues
Keywords: utilities,tools,productivity
Classifier: Programming Language :: Python :: 3
Classifier: License :: OSI Approved :: MIT License
Classifier: Operating System :: OS Independent
Classifier: Development Status :: 3 - Alpha
Classifier: Intended Audience :: Developers
Requires-Python: >=3.8
License-File: LICENSE
Requires-Dist: requests>=2.25.1
Requires-Dist: pandas>=2.2.3
Requires-Dist: pymysql>=1.1.0
Requires-Dist: tqdm>=4.66.4
Requires-Dist: numpy>=1.26.4
Requires-Dist: matplotlib>=3.8.4
Requires-Dist: scipy>=1.13.1
Requires-Dist: scikit-learn>=1.4.2
Dynamic: license-file
